odoo/addons/stock_operating_unit/README.rst
odoo/addons/stock_operating_unit/__init__.py
odoo/addons/stock_operating_unit/__manifest__.py
odoo/addons/stock_operating_unit/hooks.py
odoo/addons/stock_operating_unit/data/stock_data.xml
odoo/addons/stock_operating_unit/demo/stock_demo.xml
odoo/addons/stock_operating_unit/model/__init__.py
odoo/addons/stock_operating_unit/model/stock_location.py
odoo/addons/stock_operating_unit/model/stock_move.py
odoo/addons/stock_operating_unit/model/stock_picking.py
odoo/addons/stock_operating_unit/model/stock_warehouse.py
odoo/addons/stock_operating_unit/readme/CONFIGURATION.rst
odoo/addons/stock_operating_unit/readme/CONTRIBUTORS.rst
odoo/addons/stock_operating_unit/readme/DESCRIPTION.rst
odoo/addons/stock_operating_unit/readme/USAGE.rst
odoo/addons/stock_operating_unit/security/stock_security.xml
odoo/addons/stock_operating_unit/static/description/icon.png
odoo/addons/stock_operating_unit/static/description/index.html
odoo/addons/stock_operating_unit/tests/__init__.py
odoo/addons/stock_operating_unit/tests/test_stock_operating_unit.py
odoo/addons/stock_operating_unit/tests/test_stock_picking.py
odoo/addons/stock_operating_unit/tests/test_stock_security.py
odoo/addons/stock_operating_unit/view/stock.xml
odoo11_addon_stock_operating_unit-11.0.1.0.1.99.dev2.dist-info/METADATA
odoo11_addon_stock_operating_unit-11.0.1.0.1.99.dev2.dist-info/WHEEL
odoo11_addon_stock_operating_unit-11.0.1.0.1.99.dev2.dist-info/top_level.txt
odoo11_addon_stock_operating_unit-11.0.1.0.1.99.dev2.dist-info/RECORD
